abd/__init__.py
abd/abd.py
abd-0.0.3.dist-info/LICENSE.txt
abd-0.0.3.dist-info/METADATA
abd-0.0.3.dist-info/WHEEL
abd-0.0.3.dist-info/top_level.txt
abd-0.0.3.dist-info/RECORD
